LICENSE
README.md
setup.py
softbox/__init__.py
softbox/app.py
softbox/setup.py
softbox/soft.py
softbox.egg-info/PKG-INFO
softbox.egg-info/SOURCES.txt
softbox.egg-info/dependency_links.txt
softbox.egg-info/requires.txt
softbox.egg-info/top_level.txt