Metadata-Version: 2.2
Name: softbox
Version: 1.1
Summary: a tool for photographer to use Screen as SoftBox.
Home-page: http://blog.cycleuser.org
Author: cycleuser
Author-email: cycleuser@cycleuser.org
License-File: LICENSE
Requires-Dist: pandas
Requires-Dist: xlrd
Requires-Dist: matplotlib
Requires-Dist: pyside6
Requires-Dist: toga
Dynamic: author
Dynamic: author-email
Dynamic: home-page
Dynamic: requires-dist
Dynamic: summary
